gradlens/__about__.py
gradlens/__init__.py
gradlens/core.py
gradlens/hooks.py
gradlens/state.py
gradlens-0.2.0.dist-info/METADATA
gradlens-0.2.0.dist-info/WHEEL
gradlens-0.2.0.dist-info/licenses/LICENSE.txt
gradlens-0.2.0.dist-info/RECORD
