Metadata-Version: 2.4
Name: gradlens
Version: 0.2.0
Summary: An enterprise-grade PyTorch monitoring and analytics toolkit.
Project-URL: Homepage, https://github.com/gradlens/gradlens
Project-URL: Repository, https://github.com/gradlens/gradlens
Author-email: Mahdi Mosavi <mahdi.mosavi.nsa@gmail.com>
License-Expression: MIT
License-File: LICENSE.txt
Classifier: Development Status :: 3 - Alpha
Classifier: Intended Audience :: Developers
Classifier: Intended Audience :: Science/Research
Classifier: License :: OSI Approved :: MIT License
Classifier: Programming Language :: Python :: 3
Classifier: Programming Language :: Python :: 3.8
Classifier: Programming Language :: Python :: 3.9
Classifier: Programming Language :: Python :: 3.10
Classifier: Programming Language :: Python :: 3.11
Classifier: Topic :: Scientific/Engineering :: Artificial Intelligence
Classifier: Topic :: System :: Monitoring
Requires-Python: >=3.8
Requires-Dist: numpy
Requires-Dist: torch
